[{"participantId":0,"rent":554.99},{"participantId":1,"rent":554.99},{"participantId":2,"rent":556.55},{"participantId":3,"rent":554.99},{"participantId":4,"rent":1002.23},{"participantId":5,"rent":600.03},{"participantId":6,"rent":581.19},{"participantId":7,"rent":1013.2},{"participantId":8,"rent":1179.63},{"participantId":9,"rent":558},{"participantId":10,"rent":560.9},{"participantId":11,"rent":556.17},{"participantId":12,"rent":556.88},{"participantId":13,"rent":1301.56},{"participantId":14,"rent":1135.74},{"participantId":15,"rent":558.78},{"participantId":16,"rent":562.35},{"participantId":17,"rent":558.78},{"participantId":18,"rent":559.62},{"participantId":19,"rent":571.05},{"participantId":20,"rent":573.95},{"participantId":21,"rent":688.44},{"participantId":22,"rent":1014.55},{"participantId":23,"rent":559.62},{"participantId":24,"rent":573.95},{"participantId":25,"rent":586.99},{"participantId":26,"rent":586.99},{"participantId":27,"rent":562.57},{"participantId":28,"rent":562.57},{"participantId":29,"rent":615.98},{"participantId":30,"rent":829.03},{"participantId":31,"rent":567.36},{"participantId":32,"rent":570.14},{"participantId":33,"rent":573.34},{"participantId":34,"rent":1029.66},{"participantId":35,"rent":626.12},{"participantId":36,"rent":642.06},{"participantId":37,"rent":573.93},{"participantId":38,"rent":573.93},{"participantId":39,"rent":749.32},{"participantId":40,"rent":602.34},{"participantId":41,"rent":665.25},{"participantId":42,"rent":576.77},{"participantId":43,"rent":577.72},{"participantId":45,"rent":577.72},{"participantId":46,"rent":577.72},{"participantId":47,"rent":665.25},{"participantId":48,"rent":665.25},{"participantId":49,"rent":579.61},{"participantId":50,"rent":665.25},{"participantId":51,"rent":668.15},{"participantId":52,"rent":900.05},{"participantId":53,"rent":580.2},{"participantId":54,"rent":1556.36},{"participantId":55,"rent":668.99},{"participantId":56,"rent":1068.07},{"participantId":57,"rent":681.2},{"participantId":58,"rent":580.25},{"participantId":59,"rent":583.4},{"participantId":60,"rent":687},{"participantId":61,"rent":696.8},{"participantId":62,"rent":696.8},{"participantId":63,"rent":698.59},{"participantId":64,"rent":698.59},{"participantId":65,"rent":698.59},{"participantId":66,"rent":1174.17},{"participantId":67,"rent":698.63},{"participantId":68,"rent":701.49},{"participantId":69,"rent":1075.42},{"participantId":70,"rent":846.42},{"participantId":71,"rent":846.42},{"participantId":72,"rent":587.19},{"participantId":73,"rent":702.29},{"participantId":74,"rent":602.34},{"participantId":75,"rent":914.44},{"participantId":76,"rent":702.29},{"participantId":77,"rent":707.78},{"participantId":78,"rent":587.99},{"participantId":79,"rent":587.99},{"participantId":80,"rent":709.61},{"participantId":81,"rent":1121.11},{"participantId":82,"rent":1066.73},{"participantId":83,"rent":589.08},{"participantId":84,"rent":715.09},{"participantId":85,"rent":715.09},{"participantId":86,"rent":715.98},{"participantId":87,"rent":628.86},{"participantId":88,"rent":602.34},{"participantId":89,"rent":590.57},{"participantId":90,"rent":590.57},{"participantId":91,"rent":608.03},{"participantId":92,"rent":720.58},{"participantId":93,"rent":720.58},{"participantId":94,"rent":720.58},{"participantId":95,"rent":724.24},{"participantId":96,"rent":724.24},{"participantId":97,"rent":1014.55},{"participantId":98,"rent":724.24},{"participantId":99,"rent":726.13},{"participantId":100,"rent":597.37},{"participantId":101,"rent":600.8},{"participantId":102,"rent":602.34},{"participantId":103,"rent":602.34},{"participantId":104,"rent":628.86},{"participantId":105,"rent":839.46},{"participantId":106,"rent":898.14},{"participantId":107,"rent":726.13},{"participantId":108,"rent":602.34},{"participantId":109,"rent":603.46},{"participantId":110,"rent":603.46},{"participantId":111,"rent":608.03},{"participantId":112,"rent":740.7},{"participantId":113,"rent":1104.33},{"participantId":114,"rent":742.53},{"participantId":115,"rent":742.53},{"participantId":116,"rent":603.46},{"participantId":117,"rent":1003.9},{"participantId":118,"rent":603.46},{"participantId":119,"rent":744.36},{"participantId":120,"rent":850.82},{"participantId":121,"rent":749.32},{"participantId":122,"rent":605.32},{"participantId":123,"rent":607.99},{"participantId":124,"rent":607.99},{"participantId":125,"rent":608.03},{"participantId":126,"rent":632.65},{"participantId":128,"rent":900.05},{"participantId":129,"rent":749.32},{"participantId":130,"rent":749.32},{"participantId":131,"rent":888.46},{"participantId":132,"rent":749.32},{"participantId":133,"rent":749.32},{"participantId":134,"rent":615.6},{"participantId":135,"rent":794.25},{"participantId":136,"rent":749.32},{"participantId":137,"rent":659.17},{"participantId":138,"rent":1001.51},{"participantId":139,"rent":1263.76},{"participantId":140,"rent":615.6},{"participantId":141,"rent":829.03},{"participantId":143,"rent":615.6},{"participantId":144,"rent":751.67},{"participantId":145,"rent":623.18},{"participantId":146,"rent":751.67},{"participantId":147,"rent":751.67},{"participantId":148,"rent":615.6},{"participantId":149,"rent":623.18},{"participantId":150,"rent":615.6},{"participantId":151,"rent":615.6},{"participantId":152,"rent":758.99},{"participantId":153,"rent":885.67},{"participantId":155,"rent":615.6},{"participantId":156,"rent":760.91},{"participantId":157,"rent":616.36},{"participantId":158,"rent":768.16},{"participantId":159,"rent":616.36},{"participantId":160,"rent":617.5},{"participantId":162,"rent":775.45},{"participantId":163,"rent":617.5},{"participantId":164,"rent":1223.52},{"participantId":165,"rent":1121.11},{"participantId":166,"rent":768.16},{"participantId":167,"rent":1106.22},{"participantId":168,"rent":348.4},{"participantId":169,"rent":351.15},{"participantId":170,"rent":350.16},{"participantId":171,"rent":350.16},{"participantId":172,"rent":360.29},{"participantId":173,"rent":1014.55},{"participantId":174,"rent":421.56},{"participantId":175,"rent":360.29},{"participantId":176,"rent":509.34},{"participantId":177,"rent":363.03},{"participantId":178,"rent":1135.74},{"participantId":179,"rent":573.36},{"participantId":180,"rent":1014.55},{"participantId":181,"rent":452.65},{"participantId":182,"rent":554.01},{"participantId":183,"rent":1135.74},{"participantId":184,"rent":567.87},{"participantId":185,"rent":1135.74},{"participantId":186,"rent":1458.69},{"participantId":187,"rent":1458.69},{"participantId":188,"rent":1097.73},{"participantId":189,"rent":1097.73},{"participantId":190,"rent":366.69},{"participantId":191,"rent":366.69},{"participantId":192,"rent":1097.73},{"participantId":193,"rent":1318.55},{"participantId":194,"rent":1097.73},{"participantId":195,"rent":1318.55},{"participantId":196,"rent":372.18},{"participantId":197,"rent":635.54},{"participantId":198,"rent":1318.55},{"participantId":199,"rent":375.84},{"participantId":200,"rent":1318.55},{"participantId":201,"rent":1458.69},{"participantId":202,"rent":631.88},{"participantId":203,"rent":486.97},{"participantId":204,"rent":1458.69},{"participantId":205,"rent":350.16},{"participantId":206,"rent":376.75},{"participantId":207,"rent":1130.71},{"participantId":208,"rent":379.49},{"participantId":209,"rent":1130.71},{"participantId":210,"rent":501.11},{"participantId":211,"rent":1130.71},{"participantId":212,"rent":433.45},{"participantId":213,"rent":945.53},{"participantId":214,"rent":945.53},{"participantId":215,"rent":945.53},{"participantId":216,"rent":1130.71},{"participantId":217,"rent":550.49},{"participantId":218,"rent":523.45},{"participantId":219,"rent":773.62},{"participantId":220,"rent":673.03},{"participantId":221,"rent":872.51},{"participantId":222,"rent":386.81},{"participantId":223,"rent":567.87},{"participantId":224,"rent":773.62},{"participantId":225,"rent":773.62},{"participantId":226,"rent":955.13},{"participantId":227,"rent":395.04},{"participantId":228,"rent":872.51},{"participantId":229,"rent":1562.73},{"participantId":230,"rent":955.13},{"participantId":231,"rent":472.77},{"participantId":232,"rent":452.65},{"participantId":233,"rent":1562.73},{"participantId":234,"rent":396.87},{"participantId":235,"rent":1375.32},{"participantId":236,"rent":1375.32},{"participantId":237,"rent":1375.32},{"participantId":238,"rent":1562.73},{"participantId":239,"rent":480.08},{"participantId":240,"rent":405.1},{"participantId":241,"rent":1562.73},{"participantId":242,"rent":350.16},{"participantId":243,"rent":406.93},{"participantId":244,"rent":514.83},{"participantId":245,"rent":1475.67},{"participantId":246,"rent":502.03},{"participantId":247,"rent":523.06},{"participantId":248,"rent":1475.67},{"participantId":249,"rent":801.49},{"participantId":250,"rent":406.93},{"participantId":251,"rent":411.5},{"participantId":252,"rent":618.94},{"participantId":253,"rent":621.52},{"participantId":254,"rent":617.5},{"participantId":255,"rent":634.41},{"participantId":257,"rent":621.52},{"participantId":258,"rent":840.72},{"participantId":259,"rent":617.5},{"participantId":260,"rent":626.67},{"participantId":261,"rent":631.83},{"participantId":263,"rent":617.97},{"participantId":264,"rent":617.97},{"participantId":265,"rent":621.4},{"participantId":266,"rent":887.14},{"participantId":268,"rent":621.4},{"participantId":269,"rent":631.83},{"participantId":270,"rent":621.5},{"participantId":271,"rent":636.99},{"participantId":272,"rent":1023.4},{"participantId":273,"rent":719.51},{"participantId":274,"rent":776.25},{"participantId":275,"rent":625.07},{"participantId":276,"rent":631.9},{"participantId":277,"rent":851.45},{"participantId":278,"rent":631.9},{"participantId":280,"rent":632.65},{"participantId":281,"rent":636.99},{"participantId":282,"rent":632.65},{"participantId":283,"rent":1247.35},{"participantId":284,"rent":634.54},{"participantId":286,"rent":644.97},{"participantId":287,"rent":649.7},{"participantId":289,"rent":993.62},{"participantId":290,"rent":634.54},{"participantId":291,"rent":649.7},{"participantId":292,"rent":855.86},{"participantId":293,"rent":634.54},{"participantId":294,"rent":691.15},{"participantId":295,"rent":649.7},{"participantId":296,"rent":654.76},{"participantId":297,"rent":641.28},{"participantId":299,"rent":660.2},{"participantId":300,"rent":641.28},{"participantId":302,"rent":652.3},{"participantId":303,"rent":660.2},{"participantId":304,"rent":657.54},{"participantId":305,"rent":1001.18},{"participantId":306,"rent":657.54},{"participantId":307,"rent":760.78},{"participantId":308,"rent":659.17},{"participantId":309,"rent":659.17},{"participantId":310,"rent":659.17},{"participantId":311,"rent":691.15},{"participantId":312,"rent":659.17},{"participantId":313,"rent":659.17},{"participantId":314,"rent":665.36},{"participantId":315,"rent":659.17},{"participantId":316,"rent":659.17},{"participantId":317,"rent":667.94},{"participantId":318,"rent":678.25},{"participantId":319,"rent":659.17},{"participantId":320,"rent":678.25},{"participantId":321,"rent":1088.3},{"participantId":322,"rent":691.15},{"participantId":323,"rent":1499.25},{"participantId":324,"rent":659.17},{"participantId":325,"rent":706.16},{"participantId":326,"rent":706.16},{"participantId":327,"rent":659.17},{"participantId":328,"rent":706.16},{"participantId":329,"rent":661.06},{"participantId":330,"rent":830.41},{"participantId":331,"rent":706.16},{"participantId":332,"rent":661.06},{"participantId":333,"rent":661.06},{"participantId":334,"rent":661.87},{"participantId":335,"rent":661.87},{"participantId":336,"rent":709.42},{"participantId":337,"rent":676.33},{"participantId":338,"rent":719.51},{"participantId":339,"rent":676.33},{"participantId":340,"rent":676.33},{"participantId":341,"rent":676.33},{"participantId":342,"rent":709.42},{"participantId":343,"rent":676.33},{"participantId":344,"rent":676.33},{"participantId":345,"rent":709.42},{"participantId":347,"rent":676.33},{"participantId":348,"rent":712.67},{"participantId":349,"rent":715.93},{"participantId":350,"rent":715.93},{"participantId":351,"rent":676.33},{"participantId":353,"rent":715.93},{"participantId":354,"rent":676.33},{"participantId":355,"rent":1088.3},{"participantId":357,"rent":719.18},{"participantId":358,"rent":822.67},{"participantId":359,"rent":737.57},{"participantId":360,"rent":719.18},{"participantId":361,"rent":677.38},{"participantId":362,"rent":999.04},{"participantId":363,"rent":719.51},{"participantId":364,"rent":677.38},{"participantId":365,"rent":719.51},{"participantId":366,"rent":677.38},{"participantId":367,"rent":677.38},{"participantId":368,"rent":686.1},{"participantId":369,"rent":686.1},{"participantId":370,"rent":1088.3},{"participantId":371,"rent":719.51},{"participantId":372,"rent":831.78},{"participantId":373,"rent":1029.79},{"participantId":374,"rent":776.25},{"participantId":375,"rent":694.08},{"participantId":376,"rent":694.08},{"participantId":377,"rent":694.08},{"participantId":378,"rent":993.62},{"participantId":379,"rent":695.16},{"participantId":381,"rent":719.51},{"participantId":385,"rent":722.44},{"participantId":386,"rent":737.57},{"participantId":387,"rent":737.57},{"participantId":388,"rent":999.04},{"participantId":389,"rent":741.96},{"participantId":390,"rent":1047.86},{"participantId":391,"rent":700.32},{"participantId":393,"rent":959.99},{"participantId":394,"rent":741.96},{"participantId":395,"rent":990.3},{"participantId":396,"rent":742.72},{"participantId":397,"rent":745.21},{"participantId":398,"rent":1103.18},{"participantId":399,"rent":700.32},{"participantId":400,"rent":760.78},{"participantId":401,"rent":700.32},{"participantId":402,"rent":700.32},{"participantId":403,"rent":826.22},{"participantId":404,"rent":700.32},{"participantId":405,"rent":761.49},{"participantId":408,"rent":793.53},{"participantId":409,"rent":761.49},{"participantId":410,"rent":701.81},{"participantId":411,"rent":761.49},{"participantId":412,"rent":705.1},{"participantId":413,"rent":703.8},{"participantId":414,"rent":703.8},{"participantId":415,"rent":703.8},{"participantId":416,"rent":761.49},{"participantId":417,"rent":830.41},{"participantId":418,"rent":795.67},{"participantId":419,"rent":709.88},{"participantId":420,"rent":801.49},{"participantId":421,"rent":353.08},{"participantId":422,"rent":356.34},{"participantId":423,"rent":1475.67},{"participantId":424,"rent":530.44},{"participantId":425,"rent":356.34},{"participantId":426,"rent":370.98},{"participantId":427,"rent":431.18},{"participantId":428,"rent":1475.67},{"participantId":429,"rent":351.35},{"participantId":430,"rent":499.52},{"participantId":431,"rent":370.98},{"participantId":432,"rent":421.42},{"participantId":433,"rent":352.55},{"participantId":434,"rent":370.98},{"participantId":435,"rent":499.52},{"participantId":436,"rent":530.44},{"participantId":437,"rent":372.61},{"participantId":438,"rent":380.74},{"participantId":439,"rent":691.52},{"participantId":440,"rent":354.94},{"participantId":441,"rent":582.63},{"participantId":442,"rent":380.74},{"participantId":443,"rent":598.74},{"participantId":444,"rent":354.94},{"participantId":445,"rent":380.74},{"participantId":446,"rent":358.52},{"participantId":447,"rent":645.69},{"participantId":448,"rent":1059.93},{"participantId":449,"rent":380.74},{"participantId":450,"rent":381.91},{"participantId":451,"rent":1059.93},{"participantId":452,"rent":427.93},{"participantId":453,"rent":396.77},{"participantId":454,"rent":358.52},{"participantId":455,"rent":358.52},{"participantId":456,"rent":465.35},{"participantId":457,"rent":359.72},{"participantId":458,"rent":361.74},{"participantId":459,"rent":381.91},{"participantId":460,"rent":807.18},{"participantId":461,"rent":807.18},{"participantId":462,"rent":523.93},{"participantId":463,"rent":388.88},{"participantId":464,"rent":1029.79},{"participantId":465,"rent":1029.79},{"participantId":466,"rent":362.11},{"participantId":467,"rent":388.88},{"participantId":468,"rent":390.51},{"participantId":469,"rent":392.13},{"participantId":470,"rent":872.13},{"participantId":471,"rent":872.13},{"participantId":472,"rent":515.62},{"participantId":473,"rent":395.39},{"participantId":474,"rent":872.13},{"participantId":475,"rent":362.11},{"participantId":476,"rent":362.11},{"participantId":477,"rent":398.64},{"participantId":478,"rent":398.64},{"participantId":479,"rent":509.27},{"participantId":480,"rent":362.11},{"participantId":481,"rent":409.92},{"participantId":482,"rent":362.11},{"participantId":483,"rent":364.5},{"participantId":484,"rent":515.62},{"participantId":485,"rent":364.5},{"participantId":486,"rent":368.09},{"participantId":487,"rent":413.11},{"participantId":488,"rent":530.44},{"participantId":489,"rent":369.28},{"participantId":490,"rent":370.48},{"participantId":491,"rent":1373.28},{"participantId":492,"rent":416.54},{"participantId":493,"rent":416.54},{"participantId":494,"rent":1373.28},{"participantId":495,"rent":418.17},{"participantId":496,"rent":1373.28},{"participantId":497,"rent":475.11},{"participantId":498,"rent":423.05},{"participantId":499,"rent":374.73},{"participantId":500,"rent":372.87},{"participantId":501,"rent":509.27},{"participantId":502,"rent":427.93},{"participantId":503,"rent":519.05},{"participantId":504,"rent":710.48},{"participantId":505,"rent":715.99},{"participantId":506,"rent":717.05},{"participantId":507,"rent":713.29},{"participantId":508,"rent":804.37},{"participantId":511,"rent":713.29},{"participantId":513,"rent":720.96},{"participantId":515,"rent":724.22},{"participantId":516,"rent":724.22},{"participantId":517,"rent":729},{"participantId":518,"rent":729},{"participantId":519,"rent":734.93},{"participantId":520,"rent":720.96},{"participantId":521,"rent":731.39},{"participantId":522,"rent":723.47},{"participantId":524,"rent":724.4},{"participantId":525,"rent":724.4},{"participantId":527,"rent":734.93},{"participantId":528,"rent":727.8},{"participantId":529,"rent":738.56},{"participantId":530,"rent":740.95},{"participantId":531,"rent":727.8},{"participantId":532,"rent":732.14},{"participantId":533,"rent":748.12},{"participantId":534,"rent":738.13},{"participantId":535,"rent":748.12},{"participantId":536,"rent":738.13},{"participantId":537,"rent":791.72},{"participantId":538,"rent":748.12},{"participantId":540,"rent":786.08},{"participantId":542,"rent":738.13},{"participantId":543,"rent":760.07},{"participantId":544,"rent":760.07},{"participantId":545,"rent":760.07},{"participantId":546,"rent":748.43},{"participantId":547,"rent":748.43},{"participantId":548,"rent":749.47},{"participantId":549,"rent":749.47},{"participantId":550,"rent":767.24},{"participantId":551,"rent":767.24},{"participantId":552,"rent":749.47},{"participantId":554,"rent":767.24},{"participantId":555,"rent":776.8},{"participantId":556,"rent":776.8},{"participantId":557,"rent":779.19},{"participantId":559,"rent":836.33},{"participantId":560,"rent":749.5},{"participantId":561,"rent":749.5},{"participantId":562,"rent":753.8},{"participantId":563,"rent":991.92},{"participantId":564,"rent":807.18},{"participantId":565,"rent":973.6},{"participantId":566,"rent":779.19},{"participantId":569,"rent":779.19},{"participantId":570,"rent":784.18},{"participantId":571,"rent":784.18},{"participantId":573,"rent":773.67},{"participantId":576,"rent":839.46},{"participantId":578,"rent":759.4},{"participantId":579,"rent":1023.4},{"participantId":581,"rent":784.18},{"participantId":582,"rent":786.08},{"participantId":583,"rent":786.36},{"participantId":584,"rent":758.13},{"participantId":585,"rent":759.4},{"participantId":586,"rent":759.4},{"participantId":587,"rent":786.36},{"participantId":588,"rent":786.36},{"participantId":590,"rent":788.75},{"participantId":591,"rent":759.4},{"participantId":592,"rent":759.4},{"participantId":593,"rent":759.4},{"participantId":594,"rent":759.4},{"participantId":596,"rent":1076.66},{"participantId":597,"rent":788.75},{"participantId":598,"rent":761.49},{"participantId":600,"rent":861.84},{"participantId":601,"rent":788.75},{"participantId":606,"rent":788.75},{"participantId":607,"rent":798.31},{"participantId":608,"rent":798.31},{"participantId":609,"rent":761.49},{"participantId":610,"rent":798.31},{"participantId":612,"rent":761.49},{"participantId":613,"rent":798.31},{"participantId":614,"rent":763.83},{"participantId":616,"rent":767.2},{"participantId":618,"rent":768.11},{"participantId":619,"rent":768.11},{"participantId":620,"rent":890.74},{"participantId":622,"rent":1216.94},{"participantId":623,"rent":772.46},{"participantId":624,"rent":1000.12},{"participantId":625,"rent":772.46},{"participantId":626,"rent":988.75},{"participantId":627,"rent":772.46},{"participantId":630,"rent":798.31},{"participantId":631,"rent":772.46},{"participantId":632,"rent":772.46},{"participantId":633,"rent":773.67},{"participantId":635,"rent":813.04},{"participantId":636,"rent":776.25},{"participantId":637,"rent":813.04},{"participantId":638,"rent":778.3},{"participantId":640,"rent":855.86},{"participantId":642,"rent":778.3},{"participantId":644,"rent":778.3},{"participantId":645,"rent":778.3},{"participantId":646,"rent":1018.39},{"participantId":648,"rent":813.04},{"participantId":649,"rent":779.79},{"participantId":650,"rent":1347.85},{"participantId":651,"rent":781.2},{"participantId":652,"rent":1018.54},{"participantId":654,"rent":1047.47},{"participantId":656,"rent":781.2},{"participantId":659,"rent":1015.82},{"participantId":660,"rent":815.82},{"participantId":661,"rent":781.41},{"participantId":662,"rent":784.12},{"participantId":664,"rent":784.12},{"participantId":665,"rent":784.25},{"participantId":666,"rent":784.27},{"participantId":667,"rent":784.27},{"participantId":669,"rent":784.27},{"participantId":671,"rent":786.19},{"participantId":672,"rent":374.06},{"participantId":673,"rent":374.73},{"participantId":674,"rent":380.04},{"participantId":675,"rent":380.04},{"participantId":676,"rent":374.73},{"participantId":677,"rent":374.73},{"participantId":678,"rent":415.89},{"participantId":679,"rent":415.89},{"participantId":680,"rent":376.9},{"participantId":681,"rent":388.4},{"participantId":682,"rent":388.4},{"participantId":683,"rent":376.9},{"participantId":684,"rent":388.4},{"participantId":685,"rent":388.4},{"participantId":686,"rent":400.35},{"participantId":687,"rent":487.59},{"participantId":688,"rent":393.18},{"participantId":689,"rent":393.18},{"participantId":690,"rent":393.18},{"participantId":691,"rent":393.18},{"participantId":692,"rent":396.77},{"participantId":693,"rent":396.77},{"participantId":694,"rent":399.16},{"participantId":695,"rent":399.16},{"participantId":696,"rent":399.16},{"participantId":697,"rent":463.69},{"participantId":698,"rent":926.81},{"participantId":699,"rent":926.81},{"participantId":700,"rent":487.59},{"participantId":701,"rent":400.35},{"participantId":702,"rent":926.81},{"participantId":703,"rent":415.89},{"participantId":704,"rent":521.06},{"participantId":705,"rent":475.11},{"participantId":706,"rent":415.89},{"participantId":707,"rent":926.81},{"participantId":708,"rent":415.89},{"participantId":709,"rent":383.6},{"participantId":710,"rent":383.6},{"participantId":711,"rent":1209.85},{"participantId":712,"rent":1209.85},{"participantId":713,"rent":1209.85},{"participantId":714,"rent":933.82},{"participantId":715,"rent":415.89},{"participantId":716,"rent":933.82},{"participantId":717,"rent":1209.85},{"participantId":718,"rent":989.53},{"participantId":719,"rent":438.59},{"participantId":720,"rent":493.01},{"participantId":721,"rent":989.53},{"participantId":722,"rent":415.89},{"participantId":723,"rent":989.53},{"participantId":724,"rent":383.6},{"participantId":725,"rent":415.89},{"participantId":726,"rent":415.89},{"participantId":727,"rent":415.89},{"participantId":728,"rent":389.9},{"participantId":729,"rent":415.89},{"participantId":730,"rent":507.5},{"participantId":731,"rent":415.89},{"participantId":732,"rent":392.06},{"participantId":733,"rent":392.06},{"participantId":734,"rent":415.89},{"participantId":735,"rent":392.12},{"participantId":736,"rent":398.69},{"participantId":737,"rent":973.6},{"participantId":738,"rent":415.89},{"participantId":739,"rent":417.08},{"participantId":740,"rent":415.89},{"participantId":741,"rent":973.6},{"participantId":742,"rent":398.69},{"participantId":743,"rent":398.69},{"participantId":744,"rent":417.08},{"participantId":745,"rent":404.6},{"participantId":746,"rent":451.74},{"participantId":747,"rent":404.6},{"participantId":748,"rent":1132.16},{"participantId":749,"rent":1132.16},{"participantId":750,"rent":1132.16},{"participantId":751,"rent":689.56},{"participantId":752,"rent":1151.58},{"participantId":753,"rent":451.74},{"participantId":754,"rent":1132.16},{"participantId":755,"rent":463.69},{"participantId":758,"rent":786.19},{"participantId":759,"rent":802.77},{"participantId":763,"rent":787.9},{"participantId":764,"rent":787},{"participantId":765,"rent":1357.96},{"participantId":766,"rent":787.9},{"participantId":767,"rent":790.08},{"participantId":769,"rent":790.08},{"participantId":770,"rent":802.77},{"participantId":772,"rent":844.95},{"participantId":775,"rent":802.77},{"participantId":776,"rent":790.77},{"participantId":777,"rent":791.98},{"participantId":778,"rent":803.09},{"participantId":779,"rent":793.74},{"participantId":781,"rent":794.25},{"participantId":782,"rent":831.78},{"participantId":783,"rent":809.2},{"participantId":784,"rent":820.35},{"participantId":786,"rent":794.25},{"participantId":787,"rent":794.25},{"participantId":788,"rent":820.35},{"participantId":795,"rent":823.11},{"participantId":796,"rent":824.84},{"participantId":797,"rent":797.28},{"participantId":798,"rent":829.64},{"participantId":800,"rent":794.25},{"participantId":801,"rent":824.84},{"participantId":803,"rent":800.54},{"participantId":804,"rent":827.44},{"participantId":805,"rent":800.54},{"participantId":807,"rent":801.49},{"participantId":809,"rent":829.72},{"participantId":810,"rent":802.94},{"participantId":811,"rent":803.79},{"participantId":812,"rent":829.72},{"participantId":813,"rent":803.79},{"participantId":814,"rent":829.72},{"participantId":815,"rent":803.92},{"participantId":819,"rent":807.18},{"participantId":820,"rent":808.5},{"participantId":821,"rent":808.97},{"participantId":822,"rent":810.2},{"participantId":823,"rent":811.09},{"participantId":826,"rent":839.93},{"participantId":829,"rent":811.09},{"participantId":830,"rent":813.85},{"participantId":833,"rent":813.86},{"participantId":835,"rent":926.95},{"participantId":836,"rent":813.86},{"participantId":837,"rent":815.34},{"participantId":838,"rent":815.99},{"participantId":840,"rent":839.93},{"participantId":841,"rent":839.93},{"participantId":843,"rent":831.78},{"participantId":844,"rent":839.93},{"participantId":845,"rent":817.46},{"participantId":848,"rent":841.13},{"participantId":849,"rent":825.85},{"participantId":850,"rent":841.13},{"participantId":851,"rent":1277.77},{"participantId":852,"rent":818.59},{"participantId":854,"rent":818.89},{"participantId":857,"rent":872.21},{"participantId":861,"rent":841.13},{"participantId":863,"rent":1277.77},{"participantId":865,"rent":819.83},{"participantId":866,"rent":1129.74},{"participantId":868,"rent":829.03},{"participantId":869,"rent":841.13},{"participantId":870,"rent":895.3},{"participantId":871,"rent":819.83},{"participantId":873,"rent":819.83},{"participantId":874,"rent":1277.99},{"participantId":877,"rent":853.44},{"participantId":878,"rent":853.44},{"participantId":879,"rent":853.44},{"participantId":880,"rent":821.17},{"participantId":881,"rent":890.69},{"participantId":882,"rent":821.71},{"participantId":888,"rent":854.76},{"participantId":889,"rent":823},{"participantId":890,"rent":1311.59},{"participantId":891,"rent":854.76},{"participantId":893,"rent":861.72},{"participantId":894,"rent":861.72},{"participantId":895,"rent":865.76},{"participantId":898,"rent":870.77},{"participantId":899,"rent":870.77},{"participantId":903,"rent":823.61},{"participantId":904,"rent":824.14},{"participantId":905,"rent":872.02},{"participantId":906,"rent":831.78},{"participantId":908,"rent":872.02},{"participantId":910,"rent":872.02},{"participantId":912,"rent":1135.03},{"participantId":913,"rent":824.14},{"participantId":914,"rent":829.03},{"participantId":915,"rent":933.82},{"participantId":916,"rent":827.39},{"participantId":917,"rent":872.02},{"participantId":918,"rent":825.25},{"participantId":921,"rent":872.21},{"participantId":922,"rent":825.25},{"participantId":926,"rent":1151.58},{"participantId":927,"rent":1151.58},{"participantId":928,"rent":409.39},{"participantId":929,"rent":589.18},{"participantId":930,"rent":1151.58},{"participantId":931,"rent":639.37},{"participantId":932,"rent":409.39},{"participantId":933,"rent":411.56},{"participantId":934,"rent":419.73},{"participantId":935,"rent":411.56},{"participantId":936,"rent":413.72},{"participantId":937,"rent":413.72},{"participantId":938,"rent":463.69},{"participantId":939,"rent":584.84},{"participantId":940,"rent":933.82},{"participantId":941,"rent":589.18},{"participantId":942,"rent":604.34},{"participantId":943,"rent":426.72},{"participantId":944,"rent":628.22},{"participantId":945,"rent":614.27},{"participantId":946,"rent":933.82},{"participantId":947,"rent":419.73},{"participantId":948,"rent":660.88},{"participantId":949,"rent":426.72},{"participantId":950,"rent":419.73},{"participantId":951,"rent":686.65},{"participantId":952,"rent":419.73},{"participantId":953,"rent":660.88},{"participantId":954,"rent":426.72},{"participantId":955,"rent":419.73},{"participantId":956,"rent":420.64},{"participantId":957,"rent":427.38},{"participantId":958,"rent":422.08},{"participantId":959,"rent":427.38},{"participantId":960,"rent":494.76},{"participantId":961,"rent":1061.63},{"participantId":962,"rent":444.61},{"participantId":963,"rent":1061.63},{"participantId":964,"rent":432.88},{"participantId":965,"rent":1061.63},{"participantId":966,"rent":1061.63},{"participantId":967,"rent":567.51},{"participantId":968,"rent":479.13},{"participantId":969,"rent":422.08},{"participantId":970,"rent":422.08},{"participantId":971,"rent":428.87},{"participantId":972,"rent":435.38},{"participantId":973,"rent":429.79},{"participantId":974,"rent":435.38},{"participantId":975,"rent":431.18},{"participantId":976,"rent":431.18},{"participantId":977,"rent":437.92},{"participantId":978,"rent":440.99},{"participantId":979,"rent":440.99},{"participantId":980,"rent":450.03},{"participantId":981,"rent":457.04},{"participantId":982,"rent":433.45},{"participantId":983,"rent":433.45},{"participantId":984,"rent":519.05},{"participantId":985,"rent":436.06},{"participantId":986,"rent":436.06},{"participantId":987,"rent":439.32},{"participantId":988,"rent":439.32},{"participantId":989,"rent":465.71},{"participantId":990,"rent":587.01},{"participantId":991,"rent":453.96},{"participantId":992,"rent":441.68},{"participantId":993,"rent":601.7},{"participantId":994,"rent":574.01},{"participantId":995,"rent":465.71},{"participantId":996,"rent":465.71},{"participantId":997,"rent":453.96},{"participantId":998,"rent":472.21},{"participantId":999,"rent":455.39},{"participantId":1000,"rent":516.66},{"participantId":1001,"rent":455.39},{"participantId":1002,"rent":456.39},{"participantId":1003,"rent":472.21},{"participantId":1004,"rent":465.35},{"participantId":1005,"rent":472.21},{"participantId":1006,"rent":472.21},{"participantId":1007,"rent":506.49},{"participantId":1008,"rent":465.35},{"participantId":1009,"rent":465.35},{"participantId":1010,"rent":465.35}]